nomad_camels_driver_keysight_e5270b/keysight_e5270b.py
nomad_camels_driver_keysight_e5270b/keysight_e5270b_config.py
nomad_camels_driver_keysight_e5270b/keysight_e5270b_config_channel.py
nomad_camels_driver_keysight_e5270b/keysight_e5270b_ophyd.py
nomad_camels_driver_keysight_e5270b-0.1.2.dist-info/LICENSE.txt
nomad_camels_driver_keysight_e5270b-0.1.2.dist-info/METADATA
nomad_camels_driver_keysight_e5270b-0.1.2.dist-info/WHEEL
nomad_camels_driver_keysight_e5270b-0.1.2.dist-info/top_level.txt
nomad_camels_driver_keysight_e5270b-0.1.2.dist-info/RECORD
